LICENSE.md
MANIFEST.in
README.md
setup.py
./django_google_dork/__init__.py
./django_google_dork/admin.py
./django_google_dork/google.py
./django_google_dork/models.py
django_google_dork.egg-info/PKG-INFO
django_google_dork.egg-info/SOURCES.txt
django_google_dork.egg-info/dependency_links.txt
django_google_dork.egg-info/requires.txt
django_google_dork.egg-info/top_level.txt